<?xml version="1.0" encoding="UTF-8" standalone="yes"?>
<unit xmlns="http://www.srcML.org/srcML/src" revision="1.0.0" language="Java" filename="wrapped_functions/handleHalt_wrapped.java"><class><specifier>public</specifier> class <name>HaltHandler</name> <block>{
    
    <function><type><specifier>public</specifier> <specifier>static</specifier> <name>int</name></type> <name>handleHalt</name><parameter_list>(<parameter><decl><type><name>int</name></type> <name>processID</name></decl></parameter>)</parameter_list> <block>{<block_content>
        <if_stmt><if>if<condition>(<expr><name>processID</name> <operator>==</operator> <literal type="number">0</literal></expr>)</condition> <block>{<block_content>
            <expr_stmt><expr><call><name><name>Machine</name><operator>.</operator><name>halt</name></name><argument_list>()</argument_list></call></expr>;</expr_stmt>
        </block_content>}</block></if> <else>else <block>{<block_content>
            <comment type="line">//System.err.println( "non-root process trying to call halt" );</comment>
            <return>return <expr><operator>-</operator><literal type="number">1</literal></expr>;</return>
        </block_content>}</block></else></if_stmt>
        <expr_stmt><expr><call><name><name>Lib</name><operator>.</operator><name>assertNotReached</name></name><argument_list>( <argument><expr><literal type="string">"Machine.halt() did not halt machine!"</literal></expr></argument> )</argument_list></call></expr>;</expr_stmt>
        <return>return <expr><literal type="number">0</literal></expr>;</return>
    </block_content>}</block></function>
    
}</block></class></unit>
