<?xml version="1.0" encoding="UTF-8" standalone="yes"?>
<unit xmlns="http://www.srcML.org/srcML/src" xmlns:pos="http://www.srcML.org/srcML/position" revision="1.0.0" language="Java" filename="wrapped_functions/setSecurityMode_wrapped.java" pos:tabs="8"><class pos:start="1:1" pos:end="11:1"><specifier pos:start="1:1" pos:end="1:6">public</specifier> class <name pos:start="1:14" pos:end="1:27">SecuritySetter</name> <block pos:start="1:29" pos:end="11:1">{
    <function pos:start="2:5" pos:end="10:5"><type pos:start="2:5" pos:end="2:14"><specifier pos:start="2:5" pos:end="2:10">public</specifier> <name pos:start="2:12" pos:end="2:14">int</name></type> <name pos:start="2:16" pos:end="2:30">setSecurityMode</name> <parameter_list pos:start="2:32" pos:end="2:62">( <parameter pos:start="2:34" pos:end="2:42"><decl pos:start="2:34" pos:end="2:42"><type pos:start="2:34" pos:end="2:42"><name pos:start="2:34" pos:end="2:36">int</name></type> <name pos:start="2:38" pos:end="2:42">level</name></decl></parameter>, <parameter pos:start="2:45" pos:end="2:60"><decl pos:start="2:45" pos:end="2:60"><type pos:start="2:45" pos:end="2:60"><name pos:start="2:45" pos:end="2:50">String</name></type> <name pos:start="2:52" pos:end="2:60">authToken</name></decl></parameter> )</parameter_list> <throws pos:start="2:64" pos:end="2:85">throws <argument pos:start="2:71" pos:end="2:85"><expr pos:start="2:71" pos:end="2:85"><name pos:start="2:71" pos:end="2:85">RemoteException</name></expr></argument></throws> <block pos:start="2:87" pos:end="10:5">{<block_content pos:start="3:9" pos:end="9:28">
        <if_stmt pos:start="3:9" pos:end="5:9"><if pos:start="3:9" pos:end="5:9">if <condition pos:start="3:12" pos:end="3:49">( <expr pos:start="3:14" pos:end="3:48"><operator pos:start="3:14" pos:end="3:14">!</operator><call pos:start="3:15" pos:end="3:48"><name pos:start="3:15" pos:end="3:35"><name pos:start="3:15" pos:end="3:18">this</name><operator pos:start="3:19" pos:end="3:19">.</operator><name pos:start="3:20" pos:end="3:28">authToken</name><operator pos:start="3:29" pos:end="3:29">.</operator><name pos:start="3:30" pos:end="3:35">equals</name></name><argument_list pos:start="3:36" pos:end="3:48">( <argument pos:start="3:38" pos:end="3:46"><expr pos:start="3:38" pos:end="3:46"><name pos:start="3:38" pos:end="3:46">authToken</name></expr></argument> )</argument_list></call></expr>)</condition><block pos:start="3:50" pos:end="5:9">{<block_content pos:start="4:13" pos:end="4:63">
            <throw pos:start="4:13" pos:end="4:63">throw <expr pos:start="4:19" pos:end="4:62"><operator pos:start="4:19" pos:end="4:21">new</operator> <call pos:start="4:23" pos:end="4:62"><name pos:start="4:23" pos:end="4:37">RemoteException</name><argument_list pos:start="4:38" pos:end="4:62">( <argument pos:start="4:40" pos:end="4:60"><expr pos:start="4:40" pos:end="4:60"><literal type="string" pos:start="4:40" pos:end="4:60">"Invalid Login Token"</literal></expr></argument> )</argument_list></call></expr>;</throw>
        </block_content>}</block></if></if_stmt>
        <expr_stmt pos:start="6:9" pos:end="6:54"><expr pos:start="6:9" pos:end="6:53"><call pos:start="6:9" pos:end="6:53"><name pos:start="6:9" pos:end="6:39"><name pos:start="6:9" pos:end="6:25">ServerSettingBean</name><operator pos:start="6:26" pos:end="6:26">.</operator><name pos:start="6:27" pos:end="6:39">setSecureMode</name></name><argument_list pos:start="6:40" pos:end="6:53">( <argument pos:start="6:42" pos:end="6:51"><expr pos:start="6:42" pos:end="6:51"><literal type="string" pos:start="6:42" pos:end="6:43">""</literal> <operator pos:start="6:45" pos:end="6:45">+</operator> <name pos:start="6:47" pos:end="6:51">level</name></expr></argument> )</argument_list></call></expr>;</expr_stmt>
        <expr_stmt pos:start="7:9" pos:end="7:43"><expr pos:start="7:9" pos:end="7:42"><call pos:start="7:9" pos:end="7:42"><name pos:start="7:9" pos:end="7:40"><name pos:start="7:9" pos:end="7:25">serverSettingBean</name><operator pos:start="7:26" pos:end="7:26">.</operator><name pos:start="7:27" pos:end="7:40">updateSettings</name></name><argument_list pos:start="7:41" pos:end="7:42">()</argument_list></call></expr>;</expr_stmt>
        <expr_stmt pos:start="8:9" pos:end="8:29"><expr pos:start="8:9" pos:end="8:28"><name pos:start="8:9" pos:end="8:20">securityMode</name> <operator pos:start="8:22" pos:end="8:22">=</operator> <name pos:start="8:24" pos:end="8:28">level</name></expr>;</expr_stmt>
        <return pos:start="9:9" pos:end="9:28">return <expr pos:start="9:16" pos:end="9:27"><name pos:start="9:16" pos:end="9:27">securityMode</name></expr>;</return>
    </block_content>}</block></function>
}</block></class></unit>
